slack_clacks/__init__.py
slack_clacks/cli.py
slack_clacks/alembic/README
slack_clacks/alembic/env.py
slack_clacks/alembic/script.py.mako
slack_clacks/alembic/versions/17063f7d3880_initial_schema.py
slack_clacks/alembic/versions/6713eb6c63d1_add_app_type_to_contexts.py
slack_clacks/alembic/versions/a1b2c3d4e5f6_add_aliases_table.py
slack_clacks/auth/__init__.py
slack_clacks/auth/cert.py
slack_clacks/auth/cli.py
slack_clacks/auth/client.py
slack_clacks/auth/constants.py
slack_clacks/auth/cookie.py
slack_clacks/auth/oauth.py
slack_clacks/auth/validation.py
slack_clacks/configuration/__init__.py
slack_clacks/configuration/cli.py
slack_clacks/configuration/database.py
slack_clacks/configuration/models.py
slack_clacks/messaging/__init__.py
slack_clacks/messaging/cli.py
slack_clacks/messaging/exceptions.py
slack_clacks/messaging/operations.py
slack_clacks/rolodex/__init__.py
slack_clacks/rolodex/cli.py
slack_clacks/rolodex/data.py
slack_clacks/rolodex/models.py
slack_clacks/rolodex/operations.py
slack_clacks/skill/__init__.py
slack_clacks/skill/cli.py
slack_clacks/skill/content.py
slack_clacks-0.4.3.dist-info/METADATA
slack_clacks-0.4.3.dist-info/WHEEL
slack_clacks-0.4.3.dist-info/entry_points.txt
slack_clacks-0.4.3.dist-info/licenses/LICENSE
slack_clacks-0.4.3.dist-info/RECORD
