Metadata-Version: 2.4
Name: slack-clacks
Version: 0.4.3
Summary: the default mode of degenerate communication.
Project-URL: Homepage, https://github.com/zomglings/clacks
Project-URL: Repository, https://github.com/zomglings/clacks
Project-URL: Issues, https://github.com/zomglings/clacks/issues
Author-email: Neeraj Kashyap <nkashy1@gmail.com>
License: MIT
License-File: LICENSE
Keywords: cli,command-line,messaging,slack
Classifier: Development Status :: 3 - Alpha
Classifier: Environment :: Console
Classifier: Intended Audience :: Developers
Classifier: License :: OSI Approved :: MIT License
Classifier: Operating System :: OS Independent
Classifier: Programming Language :: Python :: 3
Classifier: Programming Language :: Python :: 3.13
Classifier: Topic :: Communications :: Chat
Classifier: Topic :: Utilities
Requires-Python: >=3.13
Requires-Dist: alembic>=1.17.2
Requires-Dist: cryptography>=44.0.0
Requires-Dist: platformdirs>=4.5.0
Requires-Dist: slack-sdk>=3.38.0
Requires-Dist: sqlalchemy>=2.0.44
